datasets2/__init__.py
datasets2/load.py
datasets2/save.py
tests/__init__.py
tests/test_save_as_parquet.py
datasets2-0.1.1.dist-info/METADATA
datasets2-0.1.1.dist-info/WHEEL
datasets2-0.1.1.dist-info/top_level.txt
datasets2-0.1.1.dist-info/RECORD
