Metadata-Version: 2.1
Name: datasets2
Version: 0.1.1
Summary: Add-ons to the huggingface `datasets`
Home-page: https://github.com/zzsi/datasets2
Author: ZZ Si
Author-email: zhangzhang.si@gmail.com
License: MIT
Requires-Python: >=3.6
Requires-Dist: datasets
Requires-Dist: Pillow
